{"cameraMode":{"drawMode":0,"name":"Shaded","section":"Shading Mode"},"sceneLighting":true,"audioPlay":false,"sceneViewState":{"m_AlwaysRefresh":false,"showFog":true,"showSkybox":true,"showFlares":true,"showImageEffects":true,"showParticleSystems":true,"showVisualEffectGraphs":true,"m_FxEnabled":true},"in2DMode":false,"pivot":{"x":1.5334253311157227,"y":0.0,"z":-3.7566356658935549},"rotation":{"x":-0.27102383971214297,"y":-0.017040466889739038,"z":0.004799613729119301,"w":-0.9624133110046387},"size":15.842741012573243,"orthographic":false}